rossum/__init__.py
rossum/argument.py
rossum/common.py
rossum/configure.py
rossum/connector.py
rossum/hook.py
rossum/main.py
rossum/option.py
rossum/password.py
rossum/queue.py
rossum/user.py
rossum/user_assignment.py
rossum/workspace.py
rossum/document/__init__.py
rossum/document/extract_data.py
rossum/helpers/__init__.py
rossum/helpers/search_content.py
rossum/lib/__init__.py
rossum/lib/api_client.py
rossum/lib/sideloading.py
rossum/schema/__init__.py
rossum/schema/commands.py
rossum/schema/upload.py
rossum/schema/xlsx.py
rossum/schema/transform/__init__.py
rossum/schema/transform/commands.py
rossum/tools/__init__.py
rossum/tools/compare.py
rossum/tools/csv_to_options.py
rossum/tools/xls_to_csv.py
rossum-3.18.0.dist-info/LICENSE
rossum-3.18.0.dist-info/METADATA
rossum-3.18.0.dist-info/WHEEL
rossum-3.18.0.dist-info/entry_points.txt
rossum-3.18.0.dist-info/top_level.txt
rossum-3.18.0.dist-info/RECORD
