Metadata-Version: 2.1
Name: rossum
Version: 3.18.0
Summary: Command line interface for controlling the Rossum platform
Home-page: https://developers.rossum.ai/
Author: Rossum developers
Author-email: support@rossum.ai
License: MIT
Project-URL: Source, https://github.com/rossumai/rossum
Project-URL: Tracker, https://github.com/rossumai/rossum/issues
Classifier: Development Status :: 5 - Production/Stable
Classifier: Intended Audience :: Developers
Classifier: Intended Audience :: System Administrators
Classifier: License :: OSI Approved :: MIT License
Classifier: Natural Language :: English
Classifier: Operating System :: OS Independent
Classifier: Programming Language :: Python
Classifier: Programming Language :: Python :: 3
Classifier: Programming Language :: Python :: 3.7
Classifier: Programming Language :: Python :: 3.8
Classifier: Programming Language :: Python :: 3.9
Requires-Python: >=3.7
License-File: LICENSE
Requires-Dist: pandas
Requires-Dist: click >=8.0.0
Requires-Dist: click-shell
Requires-Dist: xlrd >1.2.0
Requires-Dist: requests
Requires-Dist: jsondiff
Requires-Dist: tabulate
Requires-Dist: openpyxl ==3.0.10
Requires-Dist: jmespath
Requires-Dist: polling2
Requires-Dist: more-itertools
Requires-Dist: tenacity
